LICENSE
MANIFEST.in
README.md
build.zig
build.zig.zon
pyproject.toml
setup.py
src/test_zig_zon.py
src/zig_zon.zig
zig_zon.egg-info/PKG-INFO
zig_zon.egg-info/SOURCES.txt
zig_zon.egg-info/dependency_links.txt
zig_zon.egg-info/top_level.txt