Metadata-Version: 2.4
Name: zig-zon
Version: 0.1.1
Summary: a native cpython extension to parse zig object notation strings
Author-email: Tobias Simetsreiter <dasimmet@gmail.com>
Maintainer-email: Tobias Simetsreiter <dasimmet@gmail.com>
License-Expression: MIT
Project-URL: Homepage, https://gitlab.com/dasimmet/python-zig-zon
Project-URL: Issues, https://gitlab.com/dasimmet/python-zig-zon/-/issues
Keywords: zig,ziglang,zon,cpython
Classifier: Development Status :: 4 - Beta
Classifier: Intended Audience :: Developers
Classifier: Programming Language :: Python :: 3
Classifier: Programming Language :: Python :: 3.9
Requires-Python: >=3.9
License-File: LICENSE
Dynamic: license-file
